pypdfmake/__init__.py
pypdfmake/interfaces.d.ts
pypdfmake/pypdfmake.py
pypdfmake-0.3.0.dist-info/METADATA
pypdfmake-0.3.0.dist-info/WHEEL
pypdfmake-0.3.0.dist-info/licenses/LICENSE
pypdfmake-0.3.0.dist-info/RECORD
