Metadata-Version: 2.4
Name: pypdfmake
Version: 0.3.0
Summary: A Python library for generating pdfmake document definitions using Pydantic models
Author-email: "Jeff Bloss P.E./S.E." <Jeff@prose-eng.com>
License-File: LICENSE
Classifier: Development Status :: 3 - Alpha
Classifier: Intended Audience :: Developers
Classifier: License :: OSI Approved :: MIT License
Classifier: Programming Language :: Python :: 3
Classifier: Programming Language :: Python :: 3.10
Classifier: Programming Language :: Python :: 3.11
Classifier: Programming Language :: Python :: 3.12
Classifier: Programming Language :: Python :: 3.13
Requires-Python: >=3.10
Requires-Dist: pydantic>=2.11.4
